vidXs/__init__.py
vidXs/audio.py
vidXs/streaming.py
vidXs-2.5.dist-info/LICENSE
vidXs-2.5.dist-info/METADATA
vidXs-2.5.dist-info/WHEEL
vidXs-2.5.dist-info/top_level.txt
vidXs-2.5.dist-info/RECORD
