Metadata-Version: 2.1
Name: vidXs
Version: 2.5
Summary: Streaming video data via networks
Home-page: UNKNOWN
Author: shashankx86 (Shashank Pandey)
Author-email: <shashankspis20@gmail.com>
License: UNKNOWN
Keywords: python,camera stream,stream,video stream,video,sockets,screen sharing
Platform: UNKNOWN
Classifier: License :: OSI Approved :: MIT License
Classifier: Development Status :: 5 - Production/Stable
Classifier: Intended Audience :: Developers
Classifier: Intended Audience :: End Users/Desktop
Classifier: Programming Language :: Python :: 3
Classifier: Operating System :: Unix
Classifier: Operating System :: MacOS :: MacOS X
Classifier: Operating System :: Microsoft :: Windows
Requires-Dist: opencv-python
Requires-Dist: pyautogui
Requires-Dist: pyaudio
Requires-Dist: Pillow
